pyrepr/__init__.py
pyrepr/repr_json.py
pyrepr/util.py
pyrepr-0.1.0.dist-info/WHEEL
pyrepr-0.1.0.dist-info/METADATA
pyrepr-0.1.0.dist-info/RECORD
