Metadata-Version: 2.1
Name: pyrepr
Version: 0.1.0
Summary: Pretty-printing serializable objects for humans
Home-page: https://github.com/patarapolw/pyrepr
License: MIT
Author: Pacharapol Withayasakpunt
Author-email: patarapolw@gmail.com
Classifier: License :: OSI Approved :: MIT License
Classifier: Programming Language :: Python :: 2
Classifier: Programming Language :: Python :: 2.7
Classifier: Programming Language :: Python :: 3
Classifier: Programming Language :: Python :: 3.4
Classifier: Programming Language :: Python :: 3.5
Classifier: Programming Language :: Python :: 3.6
Classifier: Programming Language :: Python :: 3.7
Requires-Dist: markdownify (>=0.4.1,<0.5.0)
Requires-Dist: toml (>=0.10.0,<0.11.0)
